{
    "floorWidth": 50,
    "floorLength": 50,
    "floorMaterial": "https://storage.googleapis.com/files.renderdraw.us/renderings/public/gltf/verticalFarm/blurry-floor_tiles_06_diff_2k.jpeg",
    "internalMaterial": "https://files.renderdraw.us/temp%26trash/WALLPAPER.png",
    "externalMaterial": "https://files.renderdraw.us/temp%26trash/BRICK.png",
    "wallDepth": 0.1,
    "wallHeight": 9,
    "walls": [{
        "x1": 0,
        "y1": -1.75,
        "x2": 0,
        "y2": 1.75,
        "x1": 1,
        "y1": 40,
        "x2": 1,
        "y2": 1,
        "name": "wall1"
    }, {
        "x1": 1,
        "y1": 1,
        "x2": 10,
        "y2": 1,
        "name": "wall2"
    },
    {
        "x1": 10,
        "y1": 1,
        "x2": 10,
        "y2": 8,
        "name": "wall3"
    },
    {
        "x1": 10,
        "y1": 8,
        "x2": 30,
        "y2": 8,
        "name": "wall4"
    },
    {
        "x1": 30,
        "y1": 8,
        "x2": 30,
        "y2": 1,
        "name": "wall5"
    },
    {
        "x1": 30,
        "y1": 1,
        "x2": 40,
        "y2": 1,
        "name": "wall6"
    },
    {
        "x1": 40,
        "y1": 1,
        "x2": 40,
        "y2": 40,
        "name": "wall7"
    },
    {
        "x1": 40,
        "y1": 40,
        "x2": 1,
        "y2": 40,
        "name": "wall8"
    }]
}